cartoonizer/__init__.py
cartoonizer/cartoonize.py
cartoonizer_package-0.1.dist-info/METADATA
cartoonizer_package-0.1.dist-info/WHEEL
cartoonizer_package-0.1.dist-info/top_level.txt
cartoonizer_package-0.1.dist-info/RECORD
